odoo10_addon_document_page_work_instruction-10.0.1.1.0-nspkg.pth
odoo/addons/document_page_work_instruction/README.rst
odoo/addons/document_page_work_instruction/__init__.py
odoo/addons/document_page_work_instruction/__manifest__.py
odoo/addons/document_page_work_instruction/data/document_page.xml
odoo/addons/document_page_work_instruction/i18n/de.po
odoo/addons/document_page_work_instruction/i18n/document_page_work_instruction.pot
odoo/addons/document_page_work_instruction/i18n/es.po
odoo/addons/document_page_work_instruction/i18n/es_CO.po
odoo/addons/document_page_work_instruction/i18n/fr.po
odoo/addons/document_page_work_instruction/i18n/hr_HR.po
odoo/addons/document_page_work_instruction/i18n/nb.po
odoo/addons/document_page_work_instruction/i18n/nl_NL.po
odoo/addons/document_page_work_instruction/i18n/nn.po
odoo/addons/document_page_work_instruction/i18n/no.po
odoo/addons/document_page_work_instruction/i18n/pt.po
odoo/addons/document_page_work_instruction/i18n/pt_BR.po
odoo/addons/document_page_work_instruction/i18n/sl.po
odoo/addons/document_page_work_instruction/i18n/vi.po
odoo/addons/document_page_work_instruction/migrations/7.0.1.0/pre-migration.py
odoo/addons/document_page_work_instruction/security/work_instruction_security.xml
odoo/addons/document_page_work_instruction/static/description/icon.png
odoo/addons/document_page_work_instruction/views/document_page_work_instructions.xml
odoo10_addon_document_page_work_instruction-10.0.1.1.0.dist-info/METADATA
odoo10_addon_document_page_work_instruction-10.0.1.1.0.dist-info/WHEEL
odoo10_addon_document_page_work_instruction-10.0.1.1.0.dist-info/namespace_packages.txt
odoo10_addon_document_page_work_instruction-10.0.1.1.0.dist-info/top_level.txt
odoo10_addon_document_page_work_instruction-10.0.1.1.0.dist-info/RECORD
